<?xml version="1.0" encoding="utf-8"?>
<Items>
    <!-- Harad -->
    <Item
        id="haradrim_head"
        name="{=aom_haradrim_head_name}[Harad] Helmet I"
        subtype="head_armor"
        mesh="haradrim_head"
        culture="Culture.aserai"
        is_merchandise="true"
        weight="2.0"
        difficulty="0"
        appearance="2"
        Type="HeadArmor">
        <ItemComponent>
            <Armor
                head_armor="12"
                has_gender_variations="false"
                hair_cover_type="all"
                modifier_group="leather"
                material_type="Leather"
                beard_cover_type="all" />
        </ItemComponent>
        <Flags
            UseTeamColor="true" />
    </Item>
    <Item
        id="haradrim02_head"
        name="{=aom_haradrim02_head_name}[Harad] Helmet II - Black"
        subtype="head_armor"
        mesh="haradrim02_head"
        culture="Culture.aserai"
        is_merchandise="true"
        weight="2.0"
        difficulty="0"
        appearance="2"
        Type="HeadArmor">
        <ItemComponent>
            <Armor
                head_armor="12"
                has_gender_variations="false"
                hair_cover_type="all"
                modifier_group="leather"
                material_type="Leather"
                beard_cover_type="all" />
        </ItemComponent>
        <Flags
            UseTeamColor="true" />
    </Item>
    <Item
        id="haradrim02a_head"
        name="{=aom_haradrim02a_head_name}[Harad] Helmet II - Maroon"
        subtype="head_armor"
        mesh="haradrim02a_head"
        culture="Culture.aserai"
        is_merchandise="true"
        weight="2.0"
        difficulty="0"
        appearance="2"
        Type="HeadArmor">
        <ItemComponent>
            <Armor
                head_armor="12"
                has_gender_variations="false"
                hair_cover_type="all"
                modifier_group="leather"
                material_type="Leather"
                beard_cover_type="all" />
        </ItemComponent>
        <Flags
            UseTeamColor="true" />
    </Item>
    <Item
        id="haradrim02b_head"
        name="{=aom_haradrim02b_head_name}[Harad] Helmet II - Gray"
        subtype="head_armor"
        mesh="haradrim02b_head"
        culture="Culture.aserai"
        is_merchandise="true"
        weight="2.0"
        difficulty="0"
        appearance="2"
        Type="HeadArmor">
        <ItemComponent>
            <Armor
                head_armor="12"
                has_gender_variations="false"
                hair_cover_type="all"
                modifier_group="leather"
                material_type="Leather"
                beard_cover_type="all" />
        </ItemComponent>
        <Flags
            UseTeamColor="true" />
    </Item>
    <Item
        id="haradrim02c_head"
        name="{=aom_haradrim02c_head_name}[Harad] Helmet II - Gold"
        subtype="head_armor"
        mesh="haradrim02c_head"
        culture="Culture.aserai"
        is_merchandise="true"
        weight="2.0"
        difficulty="0"
        appearance="2"
        Type="HeadArmor">
        <ItemComponent>
            <Armor
                head_armor="12"
                has_gender_variations="false"
                hair_cover_type="all"
                modifier_group="leather"
                material_type="Leather"
                beard_cover_type="all" />
        </ItemComponent>
        <Flags
            UseTeamColor="true" />
    </Item>
    <Item
        id="harad03_helmet"
        name="{=aom_harad03_helmet_name}[Harad] Helmet III - Orange"
        subtype="head_armor"
        mesh="harad03_helmet"
        culture="Culture.aserai"
        is_merchandise="true"
        weight="2.0"
        difficulty="0"
        appearance="2"
        Type="HeadArmor">
        <ItemComponent>
            <Armor
                head_armor="15"
                has_gender_variations="false"
                hair_cover_type="all"
                modifier_group="leather"
                material_type="Leather"
                beard_cover_type="all" />
        </ItemComponent>
        <Flags
            UseTeamColor="true" />
    </Item>
    <Item
        id="harad04_helmet"
        name="{=aom_harad04_helmet_name}[Harad] Helmet IV - Red"
        subtype="head_armor"
        mesh="harad04_helmet"
        culture="Culture.aserai"
        is_merchandise="true"
        weight="2.0"
        difficulty="0"
        appearance="2"
        Type="HeadArmor">
        <ItemComponent>
            <Armor
                head_armor="17"
                has_gender_variations="false"
                hair_cover_type="all"
                modifier_group="leather"
                material_type="Leather"
                beard_cover_type="all" />
        </ItemComponent>
        <Flags
            UseTeamColor="true" />
    </Item>
    <Item
        id="harad05_v1_helmet"
        name="{=aom_harad05_v1_helmet_name}[Harad] Helmet V"
        subtype="head_armor"
        mesh="harad05_v1_helmet"
        culture="Culture.aserai"
        is_merchandise="true"
        weight="2.0"
        difficulty="0"
        appearance="2"
        Type="HeadArmor">
        <ItemComponent>
            <Armor
                head_armor="35"
                has_gender_variations="false"
                hair_cover_type="all"
                modifier_group="plate"
                material_type="Plate"
                beard_cover_type="all" />
        </ItemComponent>
        <Flags
            UseTeamColor="true" />
    </Item>
    <Item
        id="harad06_v1_helmet"
        name="{=aom_harad06_v1_helmet_name}[Harad] Serpent Guard Helmet"
        subtype="head_armor"
        mesh="harad06_v1_helmet"
        culture="Culture.aserai"
        is_merchandise="true"
        weight="2.0"
        difficulty="0"
        appearance="2"
        Type="HeadArmor">
        <ItemComponent>
            <Armor
                head_armor="35"
                has_gender_variations="false"
                hair_cover_type="all"
                modifier_group="plate"
                material_type="Plate"
                beard_cover_type="all" />
        </ItemComponent>
        <Flags
            UseTeamColor="true" />
    </Item>
    <Item
        id="harad07_helmet"
        name="{=aom_harad07_helmet_name}[Harad] Bone Helmet"
        subtype="head_armor"
        mesh="harad07_helmet"
        culture="Culture.aserai"
        is_merchandise="true"
        weight="2.0"
        difficulty="0"
        appearance="2"
        Type="HeadArmor">
        <ItemComponent>
            <Armor
                head_armor="35"
                has_gender_variations="false"
                hair_cover_type="all"
                modifier_group="plate"
                material_type="Plate"
                beard_cover_type="all" />
        </ItemComponent>
        <Flags
            UseTeamColor="true" />
    </Item>
    <Item
        id="harad08_helmet"
        name="{=aom_harad08_helmet_name}[Harad] Archer Helmet"
        subtype="head_armor"
        mesh="harad08_helmet"
        culture="Culture.aserai"
        is_merchandise="true"
        weight="2.0"
        difficulty="0"
        appearance="2"
        Type="HeadArmor">
        <ItemComponent>
            <Armor
                head_armor="20"
                has_gender_variations="false"
                hair_cover_type="all"
                modifier_group="leather"
                material_type="Leather"
                beard_cover_type="type1" />
        </ItemComponent>
        <Flags
            UseTeamColor="true" />
    </Item>
    <!-- #endregion -->
</Items>